{
  "id": "2ef950b3e4",
  "products": [
    {
      "label": "Jeans",
      "x": 200,
      "y": 320,
      "width": 370,
      "height": 560,
      "category": "textile",
      "description": "zgzrqvserbsuobvriqlvbezhvqzhvjdHVLBEUQVBVJBZDSWHJCD.JVDBQHJbvzbvzd",
      "price": "1520"
    },
    {
      "label": "Jeans",
      "x": 370,
      "y": 420,
      "width": 370,
      "height": 570,
      "category": "textile",
      "description": "zgzrqvserbsuobvriqlvbezhvqzhvjdHVLBEUQVBVJBZDSWHJCD.JVDBQHJbvzbvzd",
      "price": "1520"
    },
    {
      "label": "Jeans",
      "x": 500,
      "y": 510,
      "width": 320,
      "height": 570,
      "category": "textile",
      "description": "zgzrqvserbsuobvriqlvbezhvqzhvjdHVLBEUQVBVJBZDSWHJCD.JVDBQHJbvzbvzd",
      "price": "1520"
    },
    {
      "label": "Jeans",
      "x": 660,
      "y": 590,
      "width": 370,
      "height": 560,
      "category": "textile",
      "description": "zgzrqvserbsuobvriqlvbezhvqzhvjdHVLBEUQVBVJBZDSWHJCD.JVDBQHJbvzbvzd",
      "price": "1520"
    },
    {
      "label": "Jeans",
      "x": 780,
      "y": 670,
      "width": 390,
      "height": 550,
      "category": "textile",
      "description": "zgzrqvserbsuobvriqlvbezhvqzhvjdHVLBEUQVBVJBZDSWHJCD.JVDBQHJbvzbvzd",
      "price": "1520"
    }
  ],
  "merchant_phone": "",
  "created_at": 1772574408.6395965
}